{
  "selectedDeck": "javascript",
  "decks": {
    "javascript": {
      "currentCardIndex": 1,
      "isInRerunMode": false,
      "cards": [
        {
          "id": "8466545c8405fff5dd531c20166538284aec27e6",
          "deck": "javascript",
          "question": "What is event bubbling?",
          "answer": "The processs whereby events...",
          "lastAnsweredRight": false,
          "numRightAnswers": 3,
          "numWrongAnswers": 1,
          "lastRightAnswerTimestamp": 13123123123,
          "lastWrongAnswerTimestamp": 12313123123,
          "lastUpdated": 1447012023613,
          "lastSeen": 1447012023613
        },
        {
          "id": "aee39e846b3e41342eec9ad9586b705fb48d1756",
          "deck": "javascript",
          "question": "What is event delegation?",
          "answer": "The pattern of listening...",
          "lastAnsweredRight": true,
          "numRightAnswers": 3,
          "numWrongAnswers": 1,
          "lastRightAnswerTimestamp": 13123123123,
          "lastWrongAnswerTimestamp": 12313123123,
          "lastUpdated": 1447012023613,
          "lastSeen": 1447012023793
        }
      ]
    }
  }
}
